django_djeddit-0.3.4.dist-info/METADATA
django_djeddit-0.3.4.dist-info/RECORD
django_djeddit-0.3.4.dist-info/WHEEL
django_djeddit-0.3.4.dist-info/top_level.txt
djeddit/__init__.py
djeddit/admin.py
djeddit/apps.py
djeddit/context_processors.py
djeddit/forms.py
djeddit/models.py
djeddit/sitemaps.py
djeddit/urls.py
djeddit/views.py
djeddit/migrations/0001_initial.py
djeddit/migrations/0002_thread_locked.py
djeddit/migrations/0003_auto_20170616_0203.py
djeddit/migrations/0004_auto_20171212_1229.py
djeddit/migrations/0005_thread_is_stickied.py
djeddit/migrations/0006_thread_slug.py
djeddit/migrations/__init__.py
djeddit/static/djeddit/bower_components/bootstrap/dist/css/bootstrap-theme.css
djeddit/static/djeddit/bower_components/bootstrap/dist/css/bootstrap-theme.min.css
djeddit/static/djeddit/bower_components/bootstrap/dist/css/bootstrap.css
djeddit/static/djeddit/bower_components/bootstrap/dist/css/bootstrap.min.css
djeddit/static/djeddit/bower_components/bootstrap/dist/fonts/glyphicons-halflings-regular.eot
djeddit/static/djeddit/bower_components/bootstrap/dist/fonts/glyphicons-halflings-regular.svg
djeddit/static/djeddit/bower_components/bootstrap/dist/fonts/glyphicons-halflings-regular.ttf
djeddit/static/djeddit/bower_components/bootstrap/dist/fonts/glyphicons-halflings-regular.woff
djeddit/static/djeddit/bower_components/bootstrap/dist/fonts/glyphicons-halflings-regular.woff2
djeddit/static/djeddit/bower_components/bootstrap/dist/js/bootstrap.js
djeddit/static/djeddit/bower_components/bootstrap/dist/js/bootstrap.min.js
djeddit/static/djeddit/bower_components/bootstrap/dist/js/npm.js
djeddit/static/djeddit/bower_components/bootstrap-select/dist/css/bootstrap-select.css
djeddit/static/djeddit/bower_components/bootstrap-select/dist/css/bootstrap-select.min.css
djeddit/static/djeddit/bower_components/bootstrap-select/dist/js/bootstrap-select.js
djeddit/static/djeddit/bower_components/bootstrap-select/dist/js/bootstrap-select.min.js
djeddit/static/djeddit/bower_components/font-awesome/css/font-awesome.css
djeddit/static/djeddit/bower_components/font-awesome/css/font-awesome.min.css
